<?xml version="1.0" encoding="utf-8"?>
<!--
 Copyright (C), 2012, OpenERP - Team de Localización Argentina.
 https://launchpad.net/~openerp-l10n-ar-localization

 This program is free software: you can redistribute it and/or modify
 it under the terms of the GNU General Public License as published by
 the Free Software Foundation, either version 3 of the License, or
 (at your option) any later version.

 This program is distributed in the hope that it will be useful,
 but WITHOUT ANY WARRANTY; without even the implied warranty of
 MERCHANTABILITY or FITNESS FOR A PARTICULAR PURPOSE. See the
 GNU General Public License for more details.

 You should have received a copy of the GNU General Public License
 along with this program. If not, see <http://www.gnu.org/licenses/>.
-->
<openerp>
    <data noupdate="True">

#
# Chart of Accounts
#
        <record model="account.account.template" id="mt_a_root">
            <field name="type">view</field>
            <field name="code">0</field>
            <field name="user_type" ref="account.account_type_root"/>
            <field name="name">Plan de Cuentas</field>
        <field name="parent_id" eval="False" />
        </record>

        <record model="account.account.template" id="mt_activo">
            <field name="type">view</field>
            <field name="code">1*</field>
            <field name="user_type" ref="account.account_type_root"/>
            <field name="name">ACTIVO</field>
            <field name="parent_id" ref="mt_a_root"/>
        </record>

        <record model="account.account.template" id="mt_activo_corriente">
            <field name="type">view</field>
            <field name="code">11*</field>
            <field name="user_type" ref="account.account_type_root"/>
            <field name="name">ACTIVO CORRIENTE</field>
            <field name="parent_id" ref="mt_activo"/>
        </record>

        <record model="account.account.template" id="mt_disponibilidades">
            <field name="type">view</field>
            <field name="code">111*</field>
            <field name="user_type" ref="account.account_type_root"/>
            <field name="name">DISPONIBILIDADES</field>
            <field name="parent_id" ref="mt_activo_corriente"/>
        </record>

        <record model="account.account.template" id="mt_caja_pesos">
            <field name="type">other</field>
            <field name="code">11101</field>
            <field name="user_type" ref="account.account_type_cash"/>
            <field name="name">Caja pesos</field>
            <field name="parent_id" ref="mt_disponibilidades"/>
        </record>

        <record model="account.account.template" id="mt_caja_monex">
            <field name="type">other</field>
            <field name="code">11102</field>
            <field name="user_type" ref="account.account_type_cash"/>
            <field name="name">Caja Monex</field>
            <field name="parent_id" ref="mt_disponibilidades"/>
        </record>

        <record model="account.account.template" id="mt_fondo_fijo">
            <field name="type">other</field>
            <field name="code">11103</field>
            <field name="user_type" ref="account.account_type_cash"/>
            <field name="name">Fondo fijo</field>
            <field name="parent_id" ref="mt_disponibilidades"/>
        </record>

        <record model="account.account.template" id="mt_banco_misc">
            <field name="type">other</field>
            <field name="code">11104</field>
            <field name="user_type" ref="account.account_type_cash"/>
            <field name="name">Banco misc</field>
            <field name="parent_id" ref="mt_disponibilidades"/>
        </record>

        <record model="account.account.template" id="mt_valores_a_depositar">
            <field name="type">other</field>
            <field name="code">11105</field>
            <field name="user_type" ref="account.account_type_cash"/>
            <field name="name">Valores a depositar</field>
            <field name="parent_id" ref="mt_disponibilidades"/>
        </record>

        <record model="account.account.template" id="mt_creditos">
            <field name="type">view</field>
            <field name="code">113*</field>
            <field name="user_type" ref="account.account_type_root"/>
            <field name="name">CRÉDITOS</field>
            <field name="parent_id" ref="mt_activo_corriente"/>
        </record>

        <record model="account.account.template" id="mt_deudores_por_ventas">
            <field name="type">receivable</field>
            <field name="code">11301</field>
            <field name="user_type" ref="account.account_type_receivable"/>
            <field name="name">Deudores por ventas</field>
            <field name="parent_id" ref="mt_creditos"/>
	    <field name="reconcile" eval="True"/>
        </record>

        <record model="account.account.template" id="mt_deudores_morosos">
            <field name="type">receivable</field>
            <field name="code">11302</field>
            <field name="user_type" ref="account.account_type_receivable"/>
            <field name="name">Deudores morosos</field>
            <field name="parent_id" ref="mt_creditos"/>
        </record>

        <record model="account.account.template" id="mt_otros_creditos">
            <field name="type">view</field>
            <field name="code">114*</field>
            <field name="user_type" ref="account.account_type_root"/>
            <field name="name">OTROS CRÉDITOS</field>
            <field name="parent_id" ref="mt_activo_corriente"/>
        </record>

        <record model="account.account.template" id="mt_creditos_impuestos">
            <field name="type">view</field>
            <field name="code">1144*</field>
            <field name="user_type" ref="account.account_type_root"/>
            <field name="name">CRÉDITOS POR IMPUESTOS</field>
            <field name="parent_id" ref="mt_otros_creditos"/>
        </record>

        <record model="account.account.template" id="mt_creditos_ganancias_sociedades">
            <field name="type">view</field>
            <field name="code">11440010*</field>
            <field name="user_type" ref="account.account_type_root"/>
            <field name="name">GANANCIAS SOCIEDADES</field>
            <field name="parent_id" ref="mt_creditos_impuestos"/>
        </record>

        <record model="account.account.template" id="mt_retencion_impuestos_ganancias_sociedades">
            <field name="type">receivable</field>
            <field name="code">1144001010</field>
            <field name="user_type" ref="account.account_type_receivable"/>
            <field name="name">Retencion impuestos a las ganancias sociedades</field>
            <field name="parent_id" ref="mt_creditos_ganancias_sociedades"/>
        </record>

        <record model="account.account.template" id="mt_anticipo_impuestos_ganancias_sociedades">
            <field name="type">receivable</field>
            <field name="code">1144001020</field>
            <field name="user_type" ref="account.account_type_receivable"/>
            <field name="name">Anticipo impuestos a las ganancias sociedades</field>
            <field name="parent_id" ref="mt_creditos_ganancias_sociedades"/>
        </record>

        <record model="account.account.template" id="mt_saldo_favorable_ing_ganancias_sociedades">
            <field name="type">receivable</field>
            <field name="code">1144001030</field>
            <field name="user_type" ref="account.account_type_receivable"/>
            <field name="name">Saldo a favor ingresos a las ganancias sociedades</field>
            <field name="parent_id" ref="mt_creditos_ganancias_sociedades"/>
        </record>

        <record model="account.account.template" id="mt_creditos_ganancias_personas">
            <field name="type">view</field>
            <field name="code">11440011*</field>
            <field name="user_type" ref="account.account_type_root"/>
            <field name="name">GANANCIAS PERSONAS FISICAS</field>
            <field name="parent_id" ref="mt_creditos_impuestos"/>
        </record>

        <record model="account.account.template" id="mt_retencion_impuestos_ganancias_personas">
            <field name="type">receivable</field>
            <field name="code">1144001110</field>
            <field name="user_type" ref="account.account_type_receivable"/>
            <field name="name">Retencion impuestos a las ganancias p. fisicas</field>
            <field name="parent_id" ref="mt_creditos_ganancias_personas"/>
        </record>

        <record model="account.account.template" id="mt_anticipo_impuestos_ganancias_personas">
            <field name="type">receivable</field>
            <field name="code">1144001120</field>
            <field name="user_type" ref="account.account_type_receivable"/>
            <field name="name">Anticipo impuestos a las ganancias p. fisicas</field>
            <field name="parent_id" ref="mt_creditos_ganancias_personas"/>
        </record>

        <record model="account.account.template" id="mt_saldo_favorable_ing_ganancias_personas">
            <field name="type">receivable</field>
            <field name="code">1144001130</field>
            <field name="user_type" ref="account.account_type_receivable"/>
            <field name="name">Saldo a favor ingresos a las ganancias sociedades</field>
            <field name="parent_id" ref="mt_creditos_ganancias_personas"/>
        </record>

        <record model="account.account.template" id="mt_creditos_iibb">
            <field name="type">view</field>
            <field name="code">11440099*</field>
            <field name="user_type" ref="account.account_type_root"/>
            <field name="name">INGRESOS BRUTOS</field>
            <field name="parent_id" ref="mt_creditos_impuestos"/>
        </record>

        <record model="account.account.template" id="mt_creditos_iibb_cf">
            <field name="type">view</field>
            <field name="code">1144009900*</field>
            <field name="user_type" ref="account.account_type_root"/>
            <field name="name">INGRESOS BRUTOS CAPITAL FEDERAL</field>
            <field name="parent_id" ref="mt_creditos_iibb"/>
        </record>

        <record model="account.account.template" id="mt_percepcion_iibb_cf">
            <field name="type">receivable</field>
            <field name="code">114400990010</field>
            <field name="user_type" ref="account.account_type_receivable"/>
            <field name="name">Percepciones ingresos brutos capital federal</field>
            <field name="parent_id" ref="mt_creditos_iibb_cf"/>
        </record>

        <record model="account.account.template" id="mt_retencion_iibb_cf">
            <field name="type">receivable</field>
            <field name="code">114400990020</field>
            <field name="user_type" ref="account.account_type_receivable"/>
            <field name="name">Retencion ingresos brutos capital federal</field>
            <field name="parent_id" ref="mt_creditos_iibb_cf"/>
        </record>

        <record model="account.account.template" id="mt_creditos_iibb_ba">
            <field name="type">view</field>
            <field name="code">1144009901*</field>
            <field name="user_type" ref="account.account_type_root"/>
            <field name="name">INGRESOS BRUTOS PROV. BUENOS AIRES</field>
            <field name="parent_id" ref="mt_creditos_iibb"/>
        </record>

        <record model="account.account.template" id="mt_percepcion_iibb_ba">
            <field name="type">receivable</field>
            <field name="code">114400990110</field>
            <field name="user_type" ref="account.account_type_receivable"/>
            <field name="name">Percepciones ingresos brutos p. buenos aires</field>
            <field name="parent_id" ref="mt_creditos_iibb_ba"/>
        </record>

        <record model="account.account.template" id="mt_retencion_iibb_ba">
            <field name="type">receivable</field>
            <field name="code">114400990120</field>
            <field name="user_type" ref="account.account_type_receivable"/>
            <field name="name">Retencion ingresos brutos p. buenos aires</field>
            <field name="parent_id" ref="mt_creditos_iibb_ba"/>
        </record>

        <record model="account.account.template" id="mt_creditos_iibb_co">
            <field name="type">view</field>
            <field name="code">1144009903*</field>
            <field name="user_type" ref="account.account_type_root"/>
            <field name="name">INGRESOS BRUTOS PROV. CORDOBA</field>
            <field name="parent_id" ref="mt_creditos_iibb"/>
        </record>

        <record model="account.account.template" id="mt_percepcion_iibb_co">
            <field name="type">receivable</field>
            <field name="code">114400990310</field>
            <field name="user_type" ref="account.account_type_receivable"/>
            <field name="name">Percepciones ingresos brutos p. córdoba</field>
            <field name="parent_id" ref="mt_creditos_iibb_co"/>
        </record>

        <record model="account.account.template" id="mt_retencion_iibb_co">
            <field name="type">receivable</field>
            <field name="code">114400990320</field>
            <field name="user_type" ref="account.account_type_receivable"/>
            <field name="name">Retencion ingresos brutos p. córdoba</field>
            <field name="parent_id" ref="mt_creditos_iibb_co"/>
        </record>

        <record model="account.account.template" id="mt_creditos_iibb_sf">
            <field name="type">view</field>
            <field name="code">1144009912*</field>
            <field name="user_type" ref="account.account_type_root"/>
            <field name="name">INGRESOS BRUTOS PROV. SANTA FÉ</field>
            <field name="parent_id" ref="mt_creditos_iibb"/>
        </record>

        <record model="account.account.template" id="mt_percepcion_iibb_sf">
            <field name="type">receivable</field>
            <field name="code">114400991210</field>
            <field name="user_type" ref="account.account_type_receivable"/>
            <field name="name">Percepciones ingresos brutos p. santa fé</field>
            <field name="parent_id" ref="mt_creditos_iibb_sf"/>
        </record>

        <record model="account.account.template" id="mt_retencion_iibb_sf">
            <field name="type">receivable</field>
            <field name="code">114400991220</field>
            <field name="user_type" ref="account.account_type_receivable"/>
            <field name="name">Retencion ingresos brutos p. santa fé</field>
            <field name="parent_id" ref="mt_creditos_iibb_sf"/>
        </record>

        <record model="account.account.template" id="mt_bienes_de_cambio">
            <field name="type">view</field>
            <field name="code">115*</field>
            <field name="user_type" ref="account.account_type_root"/>
            <field name="name">BIENES DE CAMBIO</field>
            <field name="parent_id" ref="mt_activo_corriente"/>
        </record>

        <record model="account.account.template" id="mt_equipos">
            <field name="type">receivable</field>
            <field name="code">11501</field>
            <field name="user_type" ref="account.account_type_receivable"/>
            <field name="name">Equipos</field>
            <field name="parent_id" ref="mt_bienes_de_cambio"/>
        </record>

        <record model="account.account.template" id="mt_equipos_en_demo">
            <field name="type">receivable</field>
            <field name="code">11502</field>
            <field name="user_type" ref="account.account_type_receivable"/>
            <field name="name">Equipos en Demo</field>
            <field name="parent_id" ref="mt_bienes_de_cambio"/>
        </record>

        <record model="account.account.template" id="mt_activo_no_corriente">
            <field name="type">view</field>
            <field name="code">12*</field>
            <field name="user_type" ref="account.account_type_root"/>
            <field name="name">ACTIVO NO CORRIENTE</field>
            <field name="parent_id" ref="mt_activo"/>
        </record>

        <record model="account.account.template" id="mt_bienes_de_uso">
            <field name="type">view</field>
            <field name="code">124*</field>
            <field name="user_type" ref="account.account_type_root"/>
            <field name="name">BIENES DE USO</field>
            <field name="parent_id" ref="mt_activo_no_corriente"/>
        </record>

        <record model="account.account.template" id="mt_equipos_de_computacion">
            <field name="type">other</field>
            <field name="code">12401</field>
            <field name="user_type" ref="account.account_type_root"/>
            <field name="name">Equipos computación</field>
            <field name="parent_id" ref="mt_bienes_de_uso"/>
        </record>

        <record model="account.account.template" id="mt_software">
            <field name="type">other</field>
            <field name="code">12402</field>
            <field name="user_type" ref="account.account_type_asset"/>
            <field name="name">Software</field>
            <field name="parent_id" ref="mt_bienes_de_uso"/>
        </record>

        <record model="account.account.template" id="mt_instalaciones">
            <field name="type">other</field>
            <field name="code">12403</field>
            <field name="user_type" ref="account.account_type_asset"/>
            <field name="name">Instalaciones</field>
            <field name="parent_id" ref="mt_bienes_de_uso"/>
        </record>

        <record model="account.account.template" id="mt_muebles_y_utiles">
            <field name="type">other</field>
            <field name="code">12404</field>
            <field name="user_type" ref="account.account_type_asset"/>
            <field name="name">Muebles y útiles</field>
            <field name="parent_id" ref="mt_bienes_de_uso"/>
        </record>

        <record model="account.account.template" id="mt_amortizacion_acumulada_bs_uso">
            <field name="type">view</field>
            <field name="code">125*</field>
            <field name="user_type" ref="account.account_type_root"/>
            <field name="name">AMORTIZACIONES ACUMULADAS BIENES DE USO</field>
            <field name="parent_id" ref="mt_activo_no_corriente"/>
        </record>

        <record model="account.account.template" id="mt_amortizacion_acumulada_computacion">
            <field name="type">other</field>
            <field name="code">12501</field>
            <field name="user_type" ref="account.account_type_asset"/>
            <field name="name">Amortización acumulada equipos computación</field>
            <field name="parent_id" ref="mt_amortizacion_acumulada_bs_uso"/>
        </record>

        <record model="account.account.template" id="mt_amortizacion_acumulada_software">
            <field name="type">other</field>
            <field name="code">12502</field>
            <field name="user_type" ref="account.account_type_asset"/>
            <field name="name">Amortización acumulada software</field>
            <field name="parent_id" ref="mt_amortizacion_acumulada_bs_uso"/>
        </record>

        <record model="account.account.template" id="mt_amortizacion_acumulada_instalaciones">
            <field name="type">other</field>
            <field name="code">12503</field>
            <field name="user_type" ref="account.account_type_asset"/>
            <field name="name">Amortización acumulada instalaciones</field>
            <field name="parent_id" ref="mt_amortizacion_acumulada_bs_uso"/>
        </record>

        <record model="account.account.template" id="mt_amortizacion_acumulada_muebles_utiles">
            <field name="type">other</field>
            <field name="code">12504</field>
            <field name="user_type" ref="account.account_type_asset"/>
            <field name="name">Amortización acumulada muebles y útiles</field>
            <field name="parent_id" ref="mt_amortizacion_acumulada_bs_uso"/>
        </record>

        <record model="account.account.template" id="mt_pasivo">
            <field name="type">view</field>
            <field name="code">2*</field>
            <field name="user_type" ref="account.account_type_root"/>
            <field name="name">PASIVO</field>
            <field name="parent_id" ref="mt_a_root"/>
        </record>

        <record model="account.account.template" id="mt_pasivo_corriente">
            <field name="type">view</field>
            <field name="code">21*</field>
            <field name="user_type" ref="account.account_type_root"/>
            <field name="name">PASIVO CORRIENTE</field>
            <field name="parent_id" ref="mt_pasivo"/>
        </record>

        <record model="account.account.template" id="mt_deudas_sociales">
            <field name="type">view</field>
            <field name="code">211*</field>
            <field name="user_type" ref="account.account_type_root"/>
            <field name="name">DEUDAS SOCIALES</field>
            <field name="parent_id" ref="mt_pasivo_corriente"/>
        </record>

        <record model="account.account.template" id="mt_sueldos_a_pagar">
            <field name="type">payable</field>
            <field name="code">21101</field>
            <field name="user_type" ref="account.account_type_payable"/>
            <field name="name">Sueldos a pagar</field>
            <field name="parent_id" ref="mt_deudas_sociales"/>
        </record>

        <record model="account.account.template" id="mt_cargas_sociales_a_pagar">
            <field name="type">payable</field>
            <field name="code">21102</field>
            <field name="user_type" ref="account.account_type_payable"/>
            <field name="name">Cargas sociales a pagar</field>
            <field name="parent_id" ref="mt_deudas_sociales"/>
        </record>

        <record model="account.account.template" id="mt_provision_sac_a_pagar">
            <field name="type">payable</field>
            <field name="code">21103</field>
            <field name="user_type" ref="account.account_type_payable"/>
            <field name="name">Provision SAC a pagar</field>
            <field name="parent_id" ref="mt_deudas_sociales"/>
        </record>

        <record model="account.account.template" id="mt_provision_sac_cargas_sociales">
            <field name="type">payable</field>
            <field name="code">21104</field>
            <field name="user_type" ref="account.account_type_payable"/>
            <field name="name">Provision SAC cargas sociales a pagar</field>
            <field name="parent_id" ref="mt_deudas_sociales"/>
        </record>

        <record model="account.account.template" id="mt_beneficios_al_personal">
            <field name="type">payable</field>
            <field name="code">21105</field>
            <field name="user_type" ref="account.account_type_payable"/>
            <field name="name">Beneficios al personal</field>
            <field name="parent_id" ref="mt_deudas_sociales"/>
        </record>

        <record model="account.account.template" id="mt_prevision_despidos">
            <field name="type">payable</field>
            <field name="code">21106</field>
            <field name="user_type" ref="account.account_type_payable"/>
            <field name="name">Previsión Despidos</field>
            <field name="parent_id" ref="mt_deudas_sociales"/>
        </record>

        <record model="account.account.template" id="mt_deudas_fiscales">
            <field name="type">view</field>
            <field name="code">212*</field>
            <field name="user_type" ref="account.account_type_root"/>
            <field name="name">DEUDAS FISCALES</field>
            <field name="parent_id" ref="mt_pasivo_corriente"/>
        </record>

        <record model="account.account.template" id="mt_iibb_a_pagar">
            <field name="type">other</field>
            <field name="code">21201</field>
            <field name="user_type" ref="account.account_type_payable"/>
            <field name="name">Ingresos brutos a pagar</field>
            <field name="parent_id" ref="mt_deudas_fiscales"/>
        </record>

        <record model="account.account.template" id="mt_retencion_ganancias_a_depositar">
            <field name="type">other</field>
            <field name="code">21204</field>
            <field name="user_type" ref="account.account_type_payable"/>
            <field name="name">Retención ganancias a depositar</field>
            <field name="parent_id" ref="mt_deudas_fiscales"/>
        </record>

        <record model="account.account.template" id="mt_provision_impuesto_a_las_ganancias">
            <field name="type">other</field>
            <field name="code">21205</field>
            <field name="user_type" ref="account.account_type_payable"/>
            <field name="name">Provision impuesto a las ganancias</field>
            <field name="parent_id" ref="mt_deudas_fiscales"/>
        </record>

        <record model="account.account.template" id="mt_deudas_comerciales">
            <field name="type">view</field>
            <field name="code">213*</field>
            <field name="user_type" ref="account.account_type_root"/>
            <field name="name">DEUDAS COMERCIALES</field>
            <field name="parent_id" ref="mt_pasivo_corriente"/>
        </record>

        <record model="account.account.template" id="mt_pago_proveedores">
            <field name="type">payable</field>
            <field name="code">21301</field>
            <field name="user_type" ref="account.account_type_payable"/>
            <field name="name">Proveedores</field>
            <field name="parent_id" ref="mt_deudas_comerciales"/>
        </record>

        <record model="account.account.template" id="mt_anticipos_de_clientes">
            <field name="type">payable</field>
            <field name="code">21302</field>
            <field name="user_type" ref="account.account_type_payable"/>
            <field name="name">Anticipos de clientes</field>
            <field name="parent_id" ref="mt_deudas_comerciales"/>
        </record>

        <record model="account.account.template" id="mt_provisiones_varias">
            <field name="type">view</field>
            <field name="code">214*</field>
            <field name="user_type" ref="account.account_type_root"/>
            <field name="name">PROVISIONES VARIAS</field>
            <field name="parent_id" ref="mt_pasivo_corriente"/>
        </record>

        <record model="account.account.template" id="mt_provision_gastos">
            <field name="type">payable</field>
            <field name="code">21401</field>
            <field name="user_type" ref="account.account_type_payable"/>
            <field name="name">Provision gastos</field>
            <field name="parent_id" ref="mt_pasivo_corriente"/>
        </record>

        <record model="account.account.template" id="mt_pasivo_no_corriente">
            <field name="type">view</field>
            <field name="code">22*</field>
            <field name="user_type" ref="account.account_type_root"/>
            <field name="name">PASIVO NO CORRIENTE</field>
            <field name="parent_id" ref="mt_pasivo"/>
        </record>

        <record model="account.account.template" id="mt_deudas_comerciales_largo_plazo">
            <field name="type">view</field>
            <field name="code">221*</field>
            <field name="user_type" ref="account.account_type_root"/>
            <field name="name">DEUDAS COMERCIALES A LARGO PLAZO</field>
            <field name="parent_id" ref="mt_pasivo_no_corriente"/>
        </record>

        <record model="account.account.template" id="mt_proveedores_largo_plazo">
            <field name="type">payable</field>
            <field name="code">22101</field>
            <field name="user_type" ref="account.account_type_payable"/>
            <field name="name">Deudas proveedores a largo plazo</field>
            <field name="parent_id" ref="mt_deudas_comerciales_largo_plazo"/>
        </record>

        <record model="account.account.template" id="mt_otras_deudas">
            <field name="type">view</field>
            <field name="code">222*</field>
            <field name="user_type" ref="account.account_type_root"/>
            <field name="name">OTRAS DEUDAS</field>
            <field name="parent_id" ref="mt_pasivo_no_corriente"/>
        </record>

        <record model="account.account.template" id="mt_deudas_misc">
            <field name="type">payable</field>
            <field name="code">22201</field>
            <field name="user_type" ref="account.account_type_payable"/>
            <field name="name">Deudas misc</field>
            <field name="parent_id" ref="mt_otras_deudas"/>
        </record>

        <record model="account.account.template" id="mt_patrimonio_neto">
            <field name="type">view</field>
            <field name="code">3*</field>
            <field name="user_type" ref="account.account_type_root"/>
            <field name="name">PATRIMONIO NETO</field>
            <field name="parent_id" ref="mt_a_root"/>
        </record>

        <record model="account.account.template" id="mt_capital">
            <field name="type">other</field>
            <field name="code">31000</field>
            <field name="user_type" ref="account.account_type_cash_equity"/>
            <field name="name">Capital</field>
            <field name="parent_id" ref="mt_patrimonio_neto"/>
        </record>

        <record model="account.account.template" id="mt_aporte_irrevocable">
            <field name="type">other</field>
            <field name="code">32000</field>
            <field name="user_type" ref="account.account_type_cash_equity"/>
            <field name="name">Aporte irrevocable </field>
            <field name="parent_id" ref="mt_patrimonio_neto"/>
        </record>

        <record model="account.account.template" id="mt_reserva_legal">
            <field name="type">other</field>
            <field name="code">33000</field>
            <field name="user_type" ref="account.account_type_cash_equity"/>
            <field name="name">Reserva legal</field>
            <field name="parent_id" ref="mt_patrimonio_neto"/>
        </record>

        <record model="account.account.template" id="mt_resultados_no_asignados">
            <field name="type">other</field>
            <field name="code">34000</field>
            <field name="user_type" ref="account.account_type_cash_equity"/>
            <field name="name">Resultados no asignados</field>
            <field name="parent_id" ref="mt_patrimonio_neto"/>
        </record>

        <record model="account.account.template" id="mt_resultado_del_ejercicio">
            <field name="type">other</field>
            <field name="code">35000</field>
            <field name="user_type" ref="account.account_type_cash_equity"/>
            <field name="name">Resultado del ejercicio</field>
            <field name="parent_id" ref="mt_patrimonio_neto"/>
        </record>

        <record model="account.account.template" id="mt_ingresos">
            <field name="type">view</field>
            <field name="code">4*</field>
            <field name="user_type" ref="account.account_type_root"/>
            <field name="name">INGRESOS</field>
            <field name="parent_id" ref="mt_a_root"/>
        </record>

        <record model="account.account.template" id="mt_ingresos_operativos">
            <field name="type">view</field>
            <field name="code">41*</field>
            <field name="user_type" ref="account.account_type_root"/>
            <field name="name">INGRESOS OPERATIVOS</field>
            <field name="parent_id" ref="mt_ingresos"/>
        </record>

        <record model="account.account.template" id="mt_ventas">
            <field name="type">view</field>
            <field name="code">411*</field>
            <field name="user_type" ref="account.account_type_root"/>
            <field name="name">VENTAS</field>
            <field name="parent_id" ref="mt_ingresos_operativos"/>
        </record>

        <record model="account.account.template" id="mt_ingresos_ventas">
            <field name="type">other</field>
            <field name="code">41100</field>
            <field name="user_type" ref="account.account_type_income"/>
            <field name="name">Ingresos por ventas</field>
            <field name="parent_id" ref="mt_ventas"/>
        </record>

        <record model="account.account.template" id="mt_venta_de_equipos">
            <field name="type">other</field>
            <field name="code">41101</field>
            <field name="user_type" ref="account.account_type_income"/>
            <field name="name">Venta de equipos</field>
            <field name="parent_id" ref="mt_ventas"/>
        </record>

        <record model="account.account.template" id="mt_venta_de_servicios_misc">
            <field name="type">other</field>
            <field name="code">41102</field>
            <field name="user_type" ref="account.account_type_income"/>
            <field name="name">Venta servicios misc</field>
            <field name="parent_id" ref="mt_ventas"/>
        </record>

        <record model="account.account.template" id="mt_otros_ingresos">
            <field name="type">view</field>
            <field name="code">42*</field>
            <field name="user_type" ref="account.account_type_root"/>
            <field name="name">OTROS INGRESOS</field>
            <field name="parent_id" ref="mt_ingresos"/>
        </record>

        <record model="account.account.template" id="mt_ingresos_financieros">
            <field name="type">view</field>
            <field name="code">421*</field>
            <field name="user_type" ref="account.account_type_root"/>
            <field name="name">INGRESOS FINANCIEROS</field>
            <field name="parent_id" ref="mt_otros_ingresos"/>
        </record>

        <record model="account.account.template" id="mt_resultado_invesiones_financieras">
            <field name="type">other</field>
            <field name="code">42110</field>
            <field name="user_type" ref="account.account_type_income"/>
            <field name="name">Resultado de inversiones financieras</field>
            <field name="parent_id" ref="mt_ingresos_financieros"/>
        </record>

        <record model="account.account.template" id="mt_gastos">
            <field name="type">view</field>
            <field name="code">5*</field>
            <field name="user_type" ref="account.account_type_root"/>
            <field name="name">GASTOS</field>
            <field name="parent_id" ref="mt_a_root"/>
        </record>

        <record model="account.account.template" id="mt_gastos_operativos">
            <field name="type">view</field>
            <field name="code">51*</field>
            <field name="user_type" ref="account.account_type_root"/>
            <field name="name">GASTOS OPERATIVOS</field>
            <field name="parent_id" ref="mt_gastos"/>
        </record>

        <record model="account.account.template" id="mt_gastos_de_produccion">
            <field name="type">view</field>
            <field name="code">511*</field>
            <field name="user_type" ref="account.account_type_root"/>
            <field name="name">GASTOS DE PRODUCCION</field>
            <field name="parent_id" ref="mt_gastos_operativos"/>
        </record>

        <record model="account.account.template" id="mt_gastos_operativos_generales">
            <field name="type">other</field>
            <field name="code">51100</field>
            <field name="user_type" ref="account.account_type_expense"/>
            <field name="name">Gastos operativos general</field>
            <field name="parent_id" ref="mt_gastos_de_produccion"/>
        </record>

        <record model="account.account.template" id="mt_haberes">
            <field name="type">other</field>
            <field name="code">51101</field>
            <field name="user_type" ref="account.account_type_expense"/>
            <field name="name">Haberes</field>
            <field name="parent_id" ref="mt_gastos_de_produccion"/>
        </record>

        <record model="account.account.template" id="mt_cargas_sociales">
            <field name="type">other</field>
            <field name="code">51102</field>
            <field name="user_type" ref="account.account_type_expense"/>
            <field name="name">Cargas Sociales</field>
            <field name="parent_id" ref="mt_gastos_de_produccion"/>
        </record>

        <record model="account.account.template" id="mt_costo_de_equipos">
            <field name="type">other</field>
            <field name="code">51103</field>
            <field name="user_type" ref="account.account_type_expense"/>
            <field name="name">Costo de equipos</field>
            <field name="parent_id" ref="mt_gastos_de_produccion"/>
        </record>

        <record model="account.account.template" id="mt_materiales">
            <field name="type">other</field>
            <field name="code">51104</field>
            <field name="user_type" ref="account.account_type_expense"/>
            <field name="name">Materiales</field>
            <field name="parent_id" ref="mt_gastos_de_produccion"/>
        </record>

        <record model="account.account.template" id="mt_gastos_comerciales">
            <field name="type">view</field>
            <field name="code">512*</field>
            <field name="user_type" ref="account.account_type_root"/>
            <field name="name">GASTOS COMERCIALES</field>
            <field name="parent_id" ref="mt_gastos_operativos"/>
        </record>

        <record model="account.account.template" id="mt_haberes_comerciales">
            <field name="type">other</field>
            <field name="code">51201</field>
            <field name="user_type" ref="account.account_type_expense"/>
            <field name="name">Haberes comerciales</field>
            <field name="parent_id" ref="mt_gastos_comerciales"/>
        </record>

        <record model="account.account.template" id="mt_cargas_sociales_comerciales">
            <field name="type">other</field>
            <field name="code">51202</field>
            <field name="user_type" ref="account.account_type_expense"/>
            <field name="name">Cargas sociales comerciales</field>
            <field name="parent_id" ref="mt_gastos_comerciales"/>
        </record>

        <record model="account.account.template" id="mt_comisiones_comerciales">
            <field name="type">other</field>
            <field name="code">51203</field>
            <field name="user_type" ref="account.account_type_expense"/>
            <field name="name">Comisiones</field>
            <field name="parent_id" ref="mt_gastos_comerciales"/>
        </record>

        <record model="account.account.template" id="mt_publicidad">
            <field name="type">other</field>
            <field name="code">51204</field>
            <field name="user_type" ref="account.account_type_expense"/>
            <field name="name">Publicidad</field>
            <field name="parent_id" ref="mt_gastos_comerciales"/>
        </record>

        <record model="account.account.template" id="mt_gastos_de_administracion">
            <field name="type">view</field>
            <field name="code">513*</field>
            <field name="user_type" ref="account.account_type_root"/>
            <field name="name">GASTOS DE ADMINISTRACION</field>
            <field name="parent_id" ref="mt_gastos_operativos"/>
        </record>

        <record model="account.account.template" id="mt_haberes_administrativos">
            <field name="type">other</field>
            <field name="code">51301</field>
            <field name="user_type" ref="account.account_type_expense"/>
            <field name="name">Haberes administrativos</field>
            <field name="parent_id" ref="mt_gastos_de_administracion"/>
        </record>

        <record model="account.account.template" id="mt_cargas_sociales_administrativas">
            <field name="type">other</field>
            <field name="code">51302</field>
            <field name="user_type" ref="account.account_type_expense"/>
            <field name="name">Cargas sociales administrativas</field>
            <field name="parent_id" ref="mt_gastos_de_administracion"/>
        </record>

        <record model="account.account.template" id="mt_honorarios">
            <field name="type">other</field>
            <field name="code">51303</field>
            <field name="user_type" ref="account.account_type_expense"/>
            <field name="name">Honorarios</field>
            <field name="parent_id" ref="mt_gastos_de_administracion"/>
        </record>

        <record model="account.account.template" id="mt_alquileres">
            <field name="type">other</field>
            <field name="code">51304</field>
            <field name="user_type" ref="account.account_type_expense"/>
            <field name="name">Alquileres</field>
            <field name="parent_id" ref="mt_gastos_de_administracion"/>
        </record>

        <record model="account.account.template" id="mt_servicios_agua_luz_etc">
            <field name="type">other</field>
            <field name="code">51305</field>
            <field name="user_type" ref="account.account_type_expense"/>
            <field name="name">Servicios de luz, agua, etc</field>
            <field name="parent_id" ref="mt_gastos_de_administracion"/>
        </record>

        <record model="account.account.template" id="mt_mantenimiento_y_limpieza">
            <field name="type">other</field>
            <field name="code">51306</field>
            <field name="user_type" ref="account.account_type_expense"/>
            <field name="name">Mantenimiento y limpieza</field>
            <field name="parent_id" ref="mt_gastos_de_administracion"/>
        </record>

        <record model="account.account.template" id="mt_articulos_libreria">
            <field name="type">other</field>
            <field name="code">51307</field>
            <field name="user_type" ref="account.account_type_expense"/>
            <field name="name">Artículos librería</field>
        </record>

        <record model="account.account.template" id="mt_cadeteria_y_correo">
            <field name="type">other</field>
            <field name="code">51308</field>
            <field name="user_type" ref="account.account_type_expense"/>
            <field name="name">Cadetería y correo</field>
            <field name="parent_id" ref="mt_gastos_de_administracion"/>
        </record>

        <record model="account.account.template" id="mt_seguros">
            <field name="type">other</field>
            <field name="code">51309</field>
            <field name="user_type" ref="account.account_type_expense"/>
            <field name="name">Seguros</field>
            <field name="parent_id" ref="mt_gastos_de_administracion"/>
        </record>

        <record model="account.account.template" id="mt_gastos_fiscales">
            <field name="type">view</field>
            <field name="code">514*</field>
            <field name="user_type" ref="account.account_type_root"/>
            <field name="name">GASTOS FISCALES</field>
            <field name="parent_id" ref="mt_gastos_operativos"/>
        </record>

        <record model="account.account.template" id="mt_impuestos_iibb_cf">
            <field name="type">other</field>
            <field name="code">5149999</field>
            <field name="user_type" ref="account.account_type_expense"/>
            <field name="name">Impuestos ingresos brutos CABA</field>
            <field name="parent_id" ref="mt_gastos_fiscales"/>
        </record>

        <record model="account.account.template" id="mt_impuestos_iibb_ba">
            <field name="type">other</field>
            <field name="code">5142429</field>
            <field name="user_type" ref="account.account_type_expense"/>
            <field name="name">Impuestos ingresos brutos Prov. Bs. As.</field>
            <field name="parent_id" ref="mt_gastos_fiscales"/>
        </record>

        <record model="account.account.template" id="mt_impuestos_iibb_co">
            <field name="type">other</field>
            <field name="code">5142452</field>
            <field name="user_type" ref="account.account_type_expense"/>
            <field name="name">Impuestos ingresos brutos Prov. Córdoba</field>
            <field name="parent_id" ref="mt_gastos_fiscales"/>
        </record>

        <record model="account.account.template" id="mt_impuestos_iibb_sf">
            <field name="type">other</field>
            <field name="code">5149998</field>
            <field name="user_type" ref="account.account_type_expense"/>
            <field name="name">Impuestos ingresos brutos Prov. Santa Fé</field>
            <field name="parent_id" ref="mt_gastos_fiscales"/>
        </record>

        <record model="account.account.template" id="mt_impuestos_a_las_ganancias">
            <field name="type">other</field>
            <field name="code">5142424</field>
            <field name="user_type" ref="account.account_type_expense"/>
            <field name="name">Impuestos a las ganancias</field>
            <field name="parent_id" ref="mt_gastos_fiscales"/>
        </record>

        <record model="account.account.template" id="mt_impuestos_transacciones_bancarias">
            <field name="type">other</field>
            <field name="code">5149980</field>
            <field name="user_type" ref="account.account_type_expense"/>
            <field name="name">Impuestos transacciones bancarias</field>
            <field name="parent_id" ref="mt_gastos_fiscales"/>
        </record>

        <record model="account.account.template" id="mt_otros_gastos">
            <field name="type">view</field>
            <field name="code">515*</field>
            <field name="user_type" ref="account.account_type_root"/>
            <field name="name">OTROS GASTOS </field>
        </record>

        <record model="account.account.template" id="mt_intereses_y_recargos">
            <field name="type">other</field>
            <field name="code">51501</field>
            <field name="user_type" ref="account.account_type_expense"/>
            <field name="name">Intereses y recargos</field>
            <field name="parent_id" ref="mt_otros_gastos"/>
        </record>

        <record model="account.account.template" id="mt_gastos_no_operativos">
            <field name="type">view</field>
            <field name="code">52*</field>
            <field name="user_type" ref="account.account_type_root"/>
            <field name="name">GASTOS NO OPERATIVOS</field>
            <field name="parent_id" ref="mt_gastos"/>
        </record>

        <record model="account.account.template" id="mt_amortizaciones">
            <field name="type">view</field>
            <field name="code">521*</field>
            <field name="user_type" ref="account.account_type_root"/>
            <field name="name">AMORTIZACIONES</field>
            <field name="parent_id" ref="mt_gastos_no_operativos"/>
        </record>

        <record model="account.account.template" id="mt_amortizaciones_instalaciones">
            <field name="type">other</field>
            <field name="code">52101</field>
            <field name="user_type" ref="account.account_type_expense"/>
            <field name="name">Amortizaciones instalaciones</field>
            <field name="parent_id" ref="mt_amortizaciones"/>
        </record>

        <record model="account.account.template" id="mt_amortizaciones_equipos_computacion">
            <field name="type">other</field>
            <field name="code">52102</field>
            <field name="user_type" ref="account.account_type_expense"/>
            <field name="name">Amortizaciones equipos de computación</field>
            <field name="parent_id" ref="mt_amortizaciones"/>
        </record>

        <record model="account.account.template" id="mt_amortizacion_software">
            <field name="type">other</field>
            <field name="code">52103</field>
            <field name="user_type" ref="account.account_type_expense"/>
            <field name="name">Amortizacion software</field>
            <field name="parent_id" ref="mt_amortizaciones"/>
        </record>

        <record model="account.account.template" id="mt_amortizacion_muebles_y_utiles">
            <field name="type">other</field>
            <field name="code">52104</field>
            <field name="user_type" ref="account.account_type_expense"/>
            <field name="name">Amortizacion muebles y útiles</field>
            <field name="parent_id" ref="mt_amortizaciones"/>
        </record>

#
# Tax Code Templates
#
# La generación de los códigos esta dada por los valores de las tablas del AFIP.
#
# Listado de impuestos:
# http://www.afip.gob.ar/genericos/conceptosSubconceptosValidos/listadoImpuestosConSubcon.asp
# 
# Tablas generales:
# http://www.afip.gob.ar/fe/documentos/TABLAS%20GENERALES%20V.0.1%20%2026012011.xls
#
# [código de tributo][código de impuesto]:[V: Ventas, C: Compra, P: Percepción, R: Retención, B: Valor bruto de la factura]
#
        <record id="mt_tax_code_chart_root" model="account.tax.code.template">
            <field name="name">Plan de Impuestos para Monotributistas</field>
            <field name="info">Raíz de la estructura para Monotributistas. No Incluye IVA, pero si Ingresos Brutos para Capital Federal, Buenos Aires, Córdoba y Santa Fé</field>
	    <field name="code">IVAM</field>
            <field name="parent_id" eval="False"/>
        </record>

        <record model="account.tax.code.template" id="mt_tax_code_impuestos_nacionales">
            <field name="name">IMPUESTOS NACIONALES</field>
            <field name="code">01</field>
            <field name="sign">1</field>
            <field name="parent_id" ref="mt_tax_code_chart_root"/>
        </record>

        <record model="account.tax.code.template" id="mt_tax_code_impuestos_provinciales">
            <field name="name">IMPUESTOS PROVINCIALES</field>
            <field name="code">02</field>
            <field name="sign">1</field>
            <field name="parent_id" ref="mt_tax_code_chart_root"/>
        </record>

                <record model="account.tax.code.template" id="mt_tax_code_iibb_cf">
                    <field name="code">029999</field>
                    <field name="name">IIBB Capital Federal</field>
                    <field name="sign">1</field>
                    <field name="parent_id" ref="mt_tax_code_impuestos_provinciales"/>
                </record>

                        <record model="account.tax.code.template" id="mt_tax_code_iibb_cf_percepcion">
                            <field name="code">029999:P</field>
                            <field name="name">Percepción IIBB Capital Federal</field>
                            <field name="sign">-1</field>
                            <field name="parent_id" ref="mt_tax_code_iibb_cf"/>
                        </record>

                        <record model="account.tax.code.template" id="mt_tax_code_iibb_cf_retencion">
                            <field name="code">029999:R</field>
                            <field name="name">Retención IIBB Capital Federal</field>
                            <field name="sign">-1</field>
                            <field name="parent_id" ref="mt_tax_code_iibb_cf"/>
                        </record>

                        <record model="account.tax.code.template" id="mt_tax_code_iibb_cf_facturado">
                            <field name="code">029999:F</field>
                            <field name="name">Facturado IIBB Capital Federal</field>
                            <field name="sign">0.02</field>
                            <field name="parent_id" ref="mt_tax_code_iibb_cf"/>
                        </record>

                <record model="account.tax.code.template" id="mt_tax_code_iibb_ba">
                    <field name="code">022429</field>
                    <field name="name">IIBB Prov. Buenos Aires</field>
                    <field name="sign">1</field>
                    <field name="parent_id" ref="mt_tax_code_impuestos_provinciales"/>
                </record>

						<record model="account.tax.code.template" id="mt_tax_code_iibb_ba_percepcion">
							<field name="code">022429:P</field>
							<field name="name">Percepción IIBB Prov. Buenos Aires</field>
							<field name="sign">-1</field>
							<field name="parent_id" ref="mt_tax_code_iibb_ba"/>
						</record>

						<record model="account.tax.code.template" id="mt_tax_code_iibb_ba_retencion">
							<field name="code">022429:R</field>
							<field name="name">Retención IIBB Prov. Buenos Aires</field>
							<field name="sign">-1</field>
							<field name="parent_id" ref="mt_tax_code_iibb_ba"/>
						</record>

						<record model="account.tax.code.template" id="mt_tax_code_iibb_ba_facturado">
							<field name="code">022429:F</field>
							<field name="name">Facturado IIBB Prov. Buenos Aires</field>
							<field name="sign">0.02</field>
							<field name="parent_id" ref="mt_tax_code_iibb_ba"/>
						</record>

                <record model="account.tax.code.template" id="mt_tax_code_iibb_co">
                    <field name="code">022452</field>
                    <field name="name">IIBB Prov. Córdoba</field>
                    <field name="sign">1</field>
                    <field name="parent_id" ref="mt_tax_code_impuestos_provinciales"/>
                </record>

						<record model="account.tax.code.template" id="mt_tax_code_iibb_co_percepcion">
							<field name="code">022452:P</field>
							<field name="name">Percepción IIBB Prov. Córdoba</field>
							<field name="sign">-1</field>
							<field name="parent_id" ref="mt_tax_code_iibb_co"/>
						</record>

						<record model="account.tax.code.template" id="mt_tax_code_iibb_co_retencion">
							<field name="code">022452:R</field>
							<field name="name">Retención IIBB Prov. Córdoba</field>
							<field name="sign">-1</field>
							<field name="parent_id" ref="mt_tax_code_iibb_co"/>
						</record>

						<record model="account.tax.code.template" id="mt_tax_code_iibb_co_facturado">
							<field name="code">022452:F</field>
							<field name="name">Facturado IIBB Prov. Córdoba</field>
							<field name="sign">0.02</field>
							<field name="parent_id" ref="mt_tax_code_iibb_co"/>
						</record>

                <record model="account.tax.code.template" id="mt_tax_code_iibb_sf">
                    <field name="code">029998</field>
                    <field name="name">IIBB Prov. Santa Fé</field>
                    <field name="sign">1</field>
                    <field name="parent_id" ref="mt_tax_code_impuestos_provinciales"/>
                </record>

						<record model="account.tax.code.template" id="mt_tax_code_iibb_sf_percepcion">
							<field name="code">029998:P</field>
							<field name="name">Percepción IIBB Prov. Santa Fé</field>
							<field name="sign">-1</field>
							<field name="parent_id" ref="mt_tax_code_iibb_sf"/>
						</record>

						<record model="account.tax.code.template" id="mt_tax_code_iibb_sf_retencion">
							<field name="code">029998:R</field>
							<field name="name">Retención IIBB Prov. Santa Fé</field>
							<field name="sign">-1</field>
							<field name="parent_id" ref="mt_tax_code_iibb_sf"/>
						</record>

						<record model="account.tax.code.template" id="mt_tax_code_iibb_sf_facturado">
							<field name="code">029998:F</field>
							<field name="name">Facturado IIBB Prov. Santa Fé</field>
							<field name="sign">0.02</field>
							<field name="parent_id" ref="mt_tax_code_iibb_sf"/>
						</record>

#
# Chart Template
#
        <record id="mt_l10nAR_chart_template" model="account.chart.template">
            <field name="name">Plan Contable Genérico de Argentina para Monotributistas</field>
            <field name="account_root_id" ref="mt_a_root"/>
            <field name="tax_code_root_id" ref="mt_tax_code_chart_root"/>
            <field name="bank_account_view_id" ref="mt_banco_misc"/>
            <field name="property_account_receivable" ref="mt_deudores_por_ventas"/>
            <field name="property_account_payable" ref="mt_pago_proveedores"/>
            <field name="property_account_expense_categ" ref="mt_gastos_operativos_generales"/>
            <field name="property_account_income_categ" ref="mt_ingresos_ventas"/>
        </record>

#
# IIBB.
#

# CABA
        <record id="mt_tax_iibb_cf_percepcion" model="account.tax.template">
            <field name="chart_template_id" ref="mt_l10nAR_chart_template"/>
            <field name="name">Percepción de Ingresos Brutos CABA</field>
            <field name="description">029999:P</field>
            <field eval="0.02" name="amount"/>
            <field name="type">percent</field>
            <field name="tax_code_id" ref="mt_tax_code_iibb_cf_percepcion"/>
            <field name="ref_tax_code_id" ref="mt_tax_code_iibb_cf_percepcion"/>
            <field name="account_collected_id" ref="mt_percepcion_iibb_cf"/>
            <field name="account_paid_id" ref="mt_percepcion_iibb_cf"/>
            <field name="type_tax_use">purchase</field>
        </record>

        <record id="mt_tax_iibb_cf_retencion" model="account.tax.template">
            <field name="chart_template_id" ref="mt_l10nAR_chart_template"/>
            <field name="name">Retención de Ingresos Brutos CABA</field>
            <field name="description">029999:R</field>
            <field eval="0.02" name="amount"/>
            <field name="type">percent</field>
            <field name="tax_code_id" ref="mt_tax_code_iibb_cf_retencion"/>
            <field name="ref_tax_code_id" ref="mt_tax_code_iibb_cf_retencion"/>
            <field name="account_collected_id" ref="mt_retencion_iibb_cf"/>
            <field name="account_paid_id" ref="mt_retencion_iibb_cf"/>
            <field name="type_tax_use">purchase</field>
        </record>

        <record id="mt_tax_iibb_cf_facturado" model="account.tax.template">
            <field name="chart_template_id" ref="mt_l10nAR_chart_template"/>
            <field name="name">Facturación de Ingresos Brutos CABA</field>
            <field name="description">029999:F</field>
            <field eval="0.00" name="amount"/>
            <field name="type">fixed</field>
            <field name="base_code_id" ref="mt_tax_code_iibb_cf_facturado"/>
            <field name="ref_base_code_id" ref="mt_tax_code_iibb_cf_facturado"/>
            <field name="account_collected_id" ref="mt_impuestos_iibb_cf"/>
            <field name="account_paid_id" ref="mt_impuestos_iibb_cf"/>
            <field name="type_tax_use">sale</field>
        </record>

# Prov. BsAs.

        <record id="mt_tax_iibb_ba_percepcion" model="account.tax.template">
            <field name="chart_template_id" ref="mt_l10nAR_chart_template"/>
            <field name="name">Percepción de Ingresos Brutos Prov. Buenos Aires</field>
            <field name="description">022429:P</field>
            <field eval="0.02" name="amount"/>
            <field name="type">percent</field>
            <field name="tax_code_id" ref="mt_tax_code_iibb_ba_percepcion"/>
            <field name="ref_tax_code_id" ref="mt_tax_code_iibb_ba_percepcion"/>
            <field name="account_collected_id" ref="mt_percepcion_iibb_ba"/>
            <field name="account_paid_id" ref="mt_percepcion_iibb_ba"/>
            <field name="type_tax_use">purchase</field>
        </record>

        <record id="mt_tax_iibb_ba_retencion" model="account.tax.template">
            <field name="chart_template_id" ref="mt_l10nAR_chart_template"/>
            <field name="name">Retención de Ingresos Brutos Prov. Buenos Aires</field>
            <field name="description">022429:R</field>
            <field eval="0.02" name="amount"/>
            <field name="type">percent</field>
            <field name="tax_code_id" ref="mt_tax_code_iibb_ba_retencion"/>
            <field name="ref_tax_code_id" ref="mt_tax_code_iibb_ba_retencion"/>
            <field name="account_collected_id" ref="mt_retencion_iibb_ba"/>
            <field name="account_paid_id" ref="mt_retencion_iibb_ba"/>
            <field name="type_tax_use">purchase</field>
        </record>

        <record id="mt_tax_iibb_ba_facturado" model="account.tax.template">
            <field name="chart_template_id" ref="mt_l10nAR_chart_template"/>
            <field name="name">Facturación Ingresos Brutos Prov. Buenos Aires</field>
            <field name="description">022429:F</field>
            <field eval="0" name="amount"/>
            <field name="type">fixed</field>
            <field name="base_code_id" ref="mt_tax_code_iibb_ba_facturado"/>
            <field name="ref_base_code_id" ref="mt_tax_code_iibb_ba_facturado"/>
            <field name="account_collected_id" ref="mt_impuestos_iibb_ba"/>
            <field name="account_paid_id" ref="mt_impuestos_iibb_ba"/>
            <field name="type_tax_use">sale</field>
        </record>

# Prov. Córdoba.

        <record id="mt_tax_iibb_co_percepcion" model="account.tax.template">
            <field name="chart_template_id" ref="mt_l10nAR_chart_template"/>
            <field name="name">Percepción de Ingresos Brutos Prov. Córdoba</field>
            <field name="description">022452:P</field>
            <field eval="0.02" name="amount"/>
            <field name="type">percent</field>
            <field name="tax_code_id" ref="mt_tax_code_iibb_co_percepcion"/>
            <field name="ref_tax_code_id" ref="mt_tax_code_iibb_co_percepcion"/>
            <field name="account_collected_id" ref="mt_percepcion_iibb_co"/>
            <field name="account_paid_id" ref="mt_percepcion_iibb_co"/>
            <field name="type_tax_use">purchase</field>
        </record>

        <record id="mt_tax_iibb_co_retencion" model="account.tax.template">
            <field name="chart_template_id" ref="mt_l10nAR_chart_template"/>
            <field name="name">Retención de Ingresos Brutos Prov. Córdoba</field>
            <field name="description">022452:R</field>
            <field eval="0.02" name="amount"/>
            <field name="type">percent</field>
            <field name="tax_code_id" ref="mt_tax_code_iibb_co_retencion"/>
            <field name="ref_tax_code_id" ref="mt_tax_code_iibb_co_retencion"/>
            <field name="account_collected_id" ref="mt_retencion_iibb_co"/>
            <field name="account_paid_id" ref="mt_retencion_iibb_co"/>
            <field name="type_tax_use">purchase</field>
        </record>

        <record id="mt_tax_iibb_co_facturado" model="account.tax.template">
            <field name="chart_template_id" ref="mt_l10nAR_chart_template"/>
            <field name="name">Facturación Ingresos Brutos Prov. Córdoba</field>
            <field name="description">022452:F</field>
            <field eval="0" name="amount"/>
            <field name="type">fixed</field>
            <field name="base_code_id" ref="mt_tax_code_iibb_co_facturado"/>
            <field name="ref_base_code_id" ref="mt_tax_code_iibb_co_facturado"/>
            <field name="account_collected_id" ref="mt_impuestos_iibb_co"/>
            <field name="account_paid_id" ref="mt_impuestos_iibb_co"/>
            <field name="type_tax_use">sale</field>
        </record>

# Prov. Santa Fé

        <record id="mt_tax_iibb_sf_percepcion" model="account.tax.template">
            <field name="chart_template_id" ref="mt_l10nAR_chart_template"/>
            <field name="name">Percepción de Ingresos Brutos Prov. Santa Fé</field>
            <field name="description">029998:P</field>
            <field eval="0.02" name="amount"/>
            <field name="type">percent</field>
            <field name="tax_code_id" ref="mt_tax_code_iibb_sf_percepcion"/>
            <field name="ref_tax_code_id" ref="mt_tax_code_iibb_sf_percepcion"/>
            <field name="account_collected_id" ref="mt_percepcion_iibb_sf"/>
            <field name="account_paid_id" ref="mt_percepcion_iibb_sf"/>
            <field name="type_tax_use">purchase</field>
        </record>

        <record id="mt_tax_iibb_sf_retencion" model="account.tax.template">
            <field name="chart_template_id" ref="mt_l10nAR_chart_template"/>
            <field name="name">Retención de Ingresos Brutos Prov. Santa Fé</field>
            <field name="description">029998:R</field>
            <field eval="0.02" name="amount"/>
            <field name="type">percent</field>
            <field name="tax_code_id" ref="mt_tax_code_iibb_sf_retencion"/>
            <field name="ref_tax_code_id" ref="mt_tax_code_iibb_sf_retencion"/>
            <field name="account_collected_id" ref="mt_retencion_iibb_sf"/>
            <field name="account_paid_id" ref="mt_retencion_iibb_sf"/>
            <field name="type_tax_use">purchase</field>
        </record>

        <record id="mt_tax_iibb_sf_facturado" model="account.tax.template">
            <field name="chart_template_id" ref="mt_l10nAR_chart_template"/>
            <field name="name">Facturación Ingresos Brutos Prov. Santa Fé</field>
            <field name="description">029998:F</field>
            <field eval="0" name="amount"/>
            <field name="type">fixed</field>
            <field name="base_code_id" ref="mt_tax_code_iibb_sf_facturado"/>
            <field name="ref_base_code_id" ref="mt_tax_code_iibb_sf_facturado"/>
            <field name="account_collected_id" ref="mt_impuestos_iibb_sf"/>
            <field name="account_paid_id" ref="mt_impuestos_iibb_sf"/>
            <field name="type_tax_use">sale</field>
        </record>

#
# Impuestos a las Ganancias
# TODO. 

    </data>
</openerp>
