<?xml version="1.0" encoding="utf-8"?>
<openerp>
    <data>
        <record id="paperformat_argentinian_report" model="report.paperformat">
            <field name="name">Argentinian Reports A4</field>
            <field name="default" eval="True" />
            <field name="format">A4</field>
            <field name="page_height">0</field>
            <field name="page_width">0</field>
            <field name="orientation">Portrait</field>
            <field name="margin_top">110</field>
            <field name="margin_bottom">45</field>
            <field name="margin_left">10</field>
            <field name="margin_right">10</field>
            <field name="header_line" eval="False" />
            <field name="header_spacing">105</field>
            <field name="dpi">78</field>
        </record>
    </data>
</openerp>
